rtl/ai_acc/pe.sv
module pe (
    input clk,
    input rst_n,
    input load_en,
    input signed [7:0] in_left,
    input signed [31:0] in_top,
    output logic signed [7:0] out_right,
    output logic signed [31:0] out_bottom
);

    logic signed [7:0] weight_reg;

    always_ff @(posedge clk or negedge rst_n)
        if (!rst_n) begin
            out_right <= 0;
            out_bottom <= 0;
            weight_reg <= 0;
        end else if (load_en) begin
            weight_reg <= in_left;
            out_right <= in_left;
            out_bottom <= 0;
        end else begin
            out_right <= in_left;
            out_bottom <= in_top + (in_left * weight_reg);
        end

endmodule

tb/unit/ai_acc/pe_tb.sv
module pe_tb();

    logic clk;
    logic rst_n;
    logic load_en;
    logic [7:0] in_left;
    logic [31:0] in_top;
    logic [7:0] out_right;
    logic [31:0] out_bottom;

    pe uut(.clk(clk), .rst_n(rst_n), .load_en(load_en), .in_left(in_left), .in_top(in_top), .out_right(out_right), .out_bottom(out_bottom));

    always #10 clk <= ~clk;

    initial begin
        $dumpfile("sim_output/pe_dump.vcd");
        $dumpvars(0, pe_tb);

        clk = 0;
        rst_n = 0;
        load_en = 0;
        in_left = 0;
        in_top = 0;

        @(posedge clk); #1;
        @(posedge clk); #1;
        rst_n = 1;

        @(posedge clk); #1;
        load_en = 1; 
        in_left = 3;

        @(posedge clk); #1;
        load_en = 0; 
        in_left = 2;

        @(posedge clk); #1;
        in_left = 4; 
        in_top = 6;

        @(posedge clk); #1;
        in_left = -1; 
        in_top = 0;

        @(posedge clk); #1;
        @(posedge clk); #1;
        $finish;
    end

endmodule

sim_output/pe_dump.vcd
$version Generated by VerilatedVcd $end
$timescale 1ps $end
 $scope module TOP $end
  $scope module pe_tb $end
   $var wire 1 & clk $end
   $var wire 1 ' rst_n $end
   $var wire 1 ( load_en $end
   $var wire 8 ) in_left [7:0] $end
   $var wire 32 * in_top [31:0] $end
   $var wire 8 # out_right [7:0] $end
   $var wire 32 $ out_bottom [31:0] $end
   $scope module uut $end
    $var wire 1 & clk $end
    $var wire 1 ' rst_n $end
    $var wire 1 ( load_en $end
    $var wire 8 ) in_left [7:0] $end
    $var wire 32 * in_top [31:0] $end
    $var wire 8 # out_right [7:0] $end
    $var wire 32 $ out_bottom [31:0] $end
    $var wire 8 % weight_reg [7:0] $end
   $upscope $end
  $upscope $end
 $upscope $end
$enddefinitions $end


#0
b00000000 #
b00000000000000000000000000000000 $
b00000000 %
0&
0'
0(
b00000000 )
b00000000000000000000000000000000 *
#10
1&
#11
#20
0&
#30
1&
#31
1'
#40
0&
#50
1&
#51
1(
b00000011 )
#60
0&
#70
b00000011 #
b00000011 %
1&
#71
0(
b00000010 )
#80
0&
#90
b00000010 #
b00000000000000000000000000000110 $
1&
#91
b00000100 )
b00000000000000000000000000000110 *
#100
0&
#110
b00000100 #
b00000000000000000000000000010010 $
1&
#111
b11111111 )
b00000000000000000000000000000000 *
#120
0&
#130
b11111111 #
b11111111111111111111111111111101 $
1&
