tools_testing/passthrough.sv
module passthrough (clk, rst_n, i_8bit, o_8bit);

    input clk;
    input rst_n;
    input [7:0] i_8bit;
    output logic [7:0] o_8bit;

    always_ff @(posedge clk or negedge rst_n)
        if (!rst_n)
            o_8bit <= 8'b0;
        else
            o_8bit <= i_8bit;

endmodule

tools_testing/tb_passthrough.sv
module tb_passthrough();

    logic clk;
    logic rst_n;
    logic [7:0] i_8bit;
    logic [7:0] o_8bit;

    passthrough uut(.clk(clk), .rst_n(rst_n), .i_8bit(i_8bit), .o_8bit(o_8bit));

    always #20 clk <= ~clk;

    initial begin
        $dumpfile("dump.vcd");
        $dumpvars(0, tb_passthrough);

        rst_n = 0;
        clk = 0;
        i_8bit = 8'b0;

        #10 rst_n = 1;
        #20 i_8bit = 4;
        #40 i_8bit = 0;
        #20 rst_n = 0;
        #40 rst_n = 1;
        #20 i_8bit = 1;
        #20 $finish;
    end

endmodule

tools_testing/dump.vcd
$version Generated by VerilatedVcd $end
$timescale 1ps $end
 $scope module TOP $end
  $scope module tb_passthrough $end
   $var wire 1 # clk $end
   $var wire 1 $ rst_n $end
   $var wire 8 % i_8bit [7:0] $end
   $var wire 8 & o_8bit [7:0] $end
   $scope module uut $end
    $var wire 1 # clk $end
    $var wire 1 $ rst_n $end
    $var wire 8 % i_8bit [7:0] $end
    $var wire 8 & o_8bit [7:0] $end
   $upscope $end
  $upscope $end
 $upscope $end
$enddefinitions $end


#0
0#
0$
b00000000 %
b00000000 &
#10
1$
#20
1#
#30
b00000100 %
#40
0#
#60
1#
b00000100 &
#70
b00000000 %
#80
0#
#90
0$
b00000000 &
#100
1#
#120
0#
#130
1$
#140
1#
#150
b00000001 %
